README.md
setup.py
groceries_app/app.py
groceries_app/cookbook.yaml
groceries_app/cookbook_reader.py
groceries_app/start_app.py
groceries_app/start_app_norwegian.py
groceries_app/email_sender/__init__.py
groceries_app/email_sender/config.py
groceries_app/email_sender/email_sender.py
groceries_app/test/test_wunderpy.py
groceries_app/wunderlist/__init__.py
groceries_app/wunderlist/config.py
groceries_app/wunderlist/wunderlist.py
groceries_app_tobiasli.egg-info/PKG-INFO
groceries_app_tobiasli.egg-info/SOURCES.txt
groceries_app_tobiasli.egg-info/dependency_links.txt
groceries_app_tobiasli.egg-info/requires.txt
groceries_app_tobiasli.egg-info/top_level.txt