Metadata-Version: 2.1
Name: groceries-app-tobiasli
Version: 1.0.3
Summary: App for compiling shopping lists.
Home-page: https://github.com/tobiasli/groceries_app
Author: Tobias Litherland
Author-email: tobiaslland@gmail.com
License: UNKNOWN
Platform: UNKNOWN
Classifier: Programming Language :: Python :: 3
Classifier: License :: OSI Approved :: MIT License
Classifier: Operating System :: OS Independent
